pymapgis/__init__.py
pymapgis/acs.py
pymapgis/async_processing.py
pymapgis/auth/__init__.py
pymapgis/auth/api_keys.py
pymapgis/auth/middleware.py
pymapgis/auth/oauth.py
pymapgis/auth/rbac.py
pymapgis/auth/security.py
pymapgis/auth/session.py
pymapgis/cache.py
pymapgis/cli/__init__.py
pymapgis/cli/__main__.py
pymapgis/cli/main.py
pymapgis/cli.py
pymapgis/cloud/__init__.py
pymapgis/cloud/formats.py
pymapgis/deployment/__init__.py
pymapgis/deployment/cicd.py
pymapgis/deployment/cloud.py
pymapgis/deployment/docker.py
pymapgis/deployment/kubernetes.py
pymapgis/deployment/monitoring.py
pymapgis/enterprise/__init__.py
pymapgis/enterprise/auth.py
pymapgis/enterprise/oauth.py
pymapgis/enterprise/rbac.py
pymapgis/enterprise/tenants.py
pymapgis/enterprise/users.py
pymapgis/io/__init__.py
pymapgis/ml/__init__.py
pymapgis/ml/features.py
pymapgis/ml/sklearn_integration.py
pymapgis/ml/spatial_algorithms.py
pymapgis/network/__init__.py
pymapgis/performance/__init__.py
pymapgis/plotting.py
pymapgis/plugins/__init__.py
pymapgis/plugins/interfaces.py
pymapgis/plugins/registry.py
pymapgis/pointcloud/__init__.py
pymapgis/raster/__init__.py
pymapgis/raster/accessor.py
pymapgis/serve.py
pymapgis/settings.py
pymapgis/streaming/__init__.py
pymapgis/testing/__init__.py
pymapgis/testing/benchmarks.py
pymapgis/testing/integration.py
pymapgis/testing/load_testing.py
pymapgis/testing/profiling.py
pymapgis/testing/regression.py
pymapgis/tiger.py
pymapgis/vector/__init__.py
pymapgis/vector/geoarrow_utils.py
pymapgis/viz/__init__.py
pymapgis/viz/accessors.py
pymapgis/viz/deckgl_utils.py
pymapgis-1.0.2.dist-info/LICENSE
pymapgis-1.0.2.dist-info/METADATA
pymapgis-1.0.2.dist-info/WHEEL
pymapgis-1.0.2.dist-info/entry_points.txt
pymapgis-1.0.2.dist-info/RECORD
