Metadata-Version: 2.3
Name: pymapgis
Version: 1.0.2
Summary: Enterprise-Grade Modern GIS Toolkit for Python - Revolutionizing geospatial workflows with built-in data sources, intelligent caching, cloud-native processing, and enterprise authentication
License: MIT
Keywords: gis,geospatial,mapping,census,visualization,geography
Author: Nicholas Karlson
Author-email: nicholaskarlson@gmail.com
Requires-Python: >=3.10,<3.13
Classifier: Development Status :: 4 - Beta
Classifier: Intended Audience :: Developers
Classifier: Intended Audience :: Science/Research
Classifier: License :: OSI Approved :: MIT License
Classifier: Operating System :: OS Independent
Classifier: Programming Language :: Python :: 3
Classifier: Programming Language :: Python :: 3.10
Classifier: Programming Language :: Python :: 3.11
Classifier: Programming Language :: Python :: 3.12
Classifier: Topic :: Scientific/Engineering :: GIS
Classifier: Topic :: Software Development :: Libraries :: Python Modules
Classifier: Typing :: Typed
Requires-Dist: dask (>=2024.12.0,<2025.0.0)
Requires-Dist: fsspec (>=2025.5,<2026.0)
Requires-Dist: geoarrow-pyarrow (>=0.1.2,<0.2.0)
Requires-Dist: geopandas (>=1.1,<2.0)
Requires-Dist: leafmap (>=0.47.2,<0.48.0)
Requires-Dist: networkx (>=3.2,<4.0)
Requires-Dist: pandas (>=2.3.0,<3.0.0)
Requires-Dist: pyarrow (>=15.0.0,<16.0.0)
Requires-Dist: pydantic-settings (>=2.9.1,<3.0.0)
Requires-Dist: requests-cache (>=1.2.1,<2.0.0)
Requires-Dist: rioxarray (>=0.14.1,<0.15.0)
Requires-Dist: toml (>=0.10.2,<0.11.0)
Requires-Dist: typer (>=0.12.0,<0.13.0)
Requires-Dist: xarray (>=2023.12.0,<2024.0.0)
Requires-Dist: zarr (>=2.18.3,<3.0.0)
Project-URL: Documentation, https://pymapgis.github.io/core/
Project-URL: Homepage, https://github.com/pymapgis/core
Project-URL: Repository, https://github.com/pymapgis/core
